lucd/__init__.py
lucd/base.py
lucd/check.py
lucd/clear.py
lucd/download.py
lucd/driver.py
lucd/utils.py
lucd/tests/__init__.py
lucd/tests/test_driver.py
lucd-0.2.1.dist-info/LICENCE
lucd-0.2.1.dist-info/METADATA
lucd-0.2.1.dist-info/WHEEL
lucd-0.2.1.dist-info/top_level.txt
lucd-0.2.1.dist-info/RECORD
