Metadata-Version: 2.1
Name: lucd
Version: 0.2.1
Summary: Create Local Undetectable Chrome Driver
Home-page: https://github.com/SelmiAbderrahim/CreateUndetectableChromeDriver
Author: Selmi Abderrahim
Author-email: contact@selmi.tech
License: MIT
Keywords: python,undetectable,chrome,selenium,webdriver
Platform: UNKNOWN
Classifier: Development Status :: 4 - Beta
Classifier: Programming Language :: Python :: 3
Classifier: Operating System :: Microsoft :: Windows
License-File: LICENCE
Requires-Dist: beautifulsoup4 (==4.11.1)
Requires-Dist: colorama (==0.4.4)
Requires-Dist: requests (==2.27.1)
Requires-Dist: termcolor (==1.1.0)
Requires-Dist: lxml (==4.9.1)
Requires-Dist: selenium (==4.1.5)
Requires-Dist: fake-useragent (==0.1.11)
